namekox_redis/__init__.py
namekox_redis/constants.py
namekox_redis/cli/__init__.py
namekox_redis/cli/subctx/__init__.py
namekox_redis/cli/subctx/redisdb.py
namekox_redis/cli/subctx/sentinel.py
namekox_redis/core/__init__.py
namekox_redis/core/client.py
namekox_redis/core/dlock.py
namekox_redis/core/proxy.py
namekox_redis/core/sentinel.py
namekox_redis/core/dependencies/__init__.py
namekox_redis/core/dependencies/redisdb.py
namekox_redis/core/dependencies/sentinel.py
namekox_redis/core/entrypoints/__init__.py
namekox_redis/core/entrypoints/sub/__init__.py
namekox_redis/core/entrypoints/sub/handler.py
namekox_redis-0.0.26.dist-info/LICENSE
namekox_redis-0.0.26.dist-info/METADATA
namekox_redis-0.0.26.dist-info/WHEEL
namekox_redis-0.0.26.dist-info/top_level.txt
namekox_redis-0.0.26.dist-info/zip-safe
namekox_redis-0.0.26.dist-info/RECORD
